vachanatts/TH_G2P.py
vachanatts/__init__.py
vachanatts/config.py
vachanatts/en2th.py
vachanatts/main.py
vachanatts/phoneme_ids.py
vachanatts/text_cleaner.py
vachanatts/th_phonemizer.py
vachanatts/voice.py
vachanatts/data/PhSTrigram.sts
vachanatts/data/dict_transliteration.txt
vachanatts/data/sylrule.lts
vachanatts/data/sylseg.3g
vachanatts/data/thai2phone.csv
vachanatts/data/thaisyl.dict
vachanatts/data/thdict
vachanatts1/TH_G2P.py
vachanatts1/__init__.py
vachanatts1/config.py
vachanatts1/en2th.py
vachanatts1/main.py
vachanatts1/phoneme_ids.py
vachanatts1/text_cleaner.py
vachanatts1/th_phonemizer.py
vachanatts1/voice.py
vachanatts-0.0.7.dist-info/METADATA
vachanatts-0.0.7.dist-info/WHEEL
vachanatts-0.0.7.dist-info/top_level.txt
vachanatts-0.0.7.dist-info/RECORD
