Metadata-Version: 2.4
Name: vachanatts
Version: 0.0.7
Summary: VachanaTTS Text-to-Speech ภาษาไทย รวดเร็วและใช้งานง่าย.
Requires-Dist: pythainlp
Requires-Dist: ssg
Requires-Dist: onnxruntime
Dynamic: description
Dynamic: description-content-type
Dynamic: requires-dist
Dynamic: summary
